pystall/__init__.py
pystall/cli.py
pystall/core.py
pystall/library.py
pystall-0.3.0.dist-info/LICENSE
pystall-0.3.0.dist-info/METADATA
pystall-0.3.0.dist-info/WHEEL
pystall-0.3.0.dist-info/top_level.txt
pystall-0.3.0.dist-info/RECORD
