Metadata-Version: 2.1
Name: pystall
Version: 0.3.0
Summary: A system to automate configuration and setup of fresh Operating systems.
Home-page: UNKNOWN
Author: Kieran Wood
Author-email: kieran@canadiancoding.ca
License: UNKNOWN
Project-URL: Docs, http://pystall.readthedocs.io/
Project-URL: Bug Reports, https://github.com/Descent098/pystall
Project-URL: Source, https://github.com/Descent098/pystall
Project-URL: Roadmap, https://github.com/Descent098/pystall/projects
Platform: UNKNOWN
Classifier: Programming Language :: Python :: 3
Classifier: Operating System :: OS Independent
Requires-Dist: requests
Requires-Dist: docopt
Requires-Dist: tqdm
Requires-Dist: colored
Requires-Dist: pyinstaller
Requires-Dist: distro
Requires-Dist: pyyaml
Provides-Extra: dev
Requires-Dist: nox ; extra == 'dev'
Requires-Dist: pytest ; extra == 'dev'
Requires-Dist: mkdocs ; extra == 'dev'
